cv_parser_espanol/__init__.py
cv_parser_espanol/cv_parser_espanol.py
cv_parser_espanol-0.2.8.dist-info/METADATA
cv_parser_espanol-0.2.8.dist-info/WHEEL
cv_parser_espanol-0.2.8.dist-info/top_level.txt
cv_parser_espanol-0.2.8.dist-info/RECORD
