Metadata-Version: 2.1
Name: cv-parser-espanol
Version: 0.2.8
Requires-Dist: spacy
Requires-Dist: PyMuPDF
